iasei_apiui/__init__.py
iasei_apiui/apps.py
iasei_apiui/urls.py
iasei_apiui/views.py
iasei_apiui/static/ui/index.html
iasei_apiui/static/ui/assets/index-Cy5iR63f.js
iasei_apiui/static/ui/assets/index-De8dHN2O.css
iasei_apiui-0.1.7.dist-info/licenses/LICENSE
iasei_apiui-0.1.7.dist-info/METADATA
iasei_apiui-0.1.7.dist-info/WHEEL
iasei_apiui-0.1.7.dist-info/top_level.txt
iasei_apiui-0.1.7.dist-info/RECORD
