Metadata-Version: 2.4
Name: iasei-apiui
Version: 0.1.7
Summary: iasei-admin 插件：基于 Vue 的 Swagger UI 界面
Home-page: https://github.com/yourname/iasei-apiui
Author: Your Name
Author-email: your@email.com
Classifier: Framework :: Django
Classifier: Framework :: Django :: 4.2
Classifier: Programming Language :: Python :: 3.8
Classifier: Programming Language :: Python :: 3.9
Requires-Python: >=3.8
License-File: LICENSE
Dynamic: license-file
